{
    "services": [
        {
            "title": "LEASING & MARKETING",
            "description": "Fast tenant placement with marketing, showings, screening, and leasing.",
            "image": "/wwd/resident_screening.png"
        },
        {
            "title": "RENT COLLECTION",
            "description": "Seamless rent collection and real-time financial reporting.",
            "image": "/wwd/rent_collection.png"
        },
        {
            "title": "MAINTENANCE",
            "description": "In-house maintenance team for faster service, lower costs, and reliable repairs.",
            "image": "/wwd/maintenance.png"
        },
        {
            "title": "COMPLIANCE & TENANT Management",
            "description": "Regular inspections, lease enforcement, and full legal compliance to protect your property.",
            "image": "/wwd/resident_communication.png"
        }
    ]
} 
